{
  "parts": [
    {
      "name": "special_characters",
      "hooks": {
        "eejsBlock_editbarMenuLeft": "ep_glorantha_runes/hooks:eejsBlock_editbarMenuLeft",
        "eejsBlock_scripts": "ep_glorantha_runes/hooks:eejsBlock_scripts",
        "eejsBlock_styles": "ep_glorantha_runes/hooks:eejsBlock_styles",
        "eejsBlock_body": "ep_glorantha_runes/hooks:eejsBlock_body",
        "eejsBlock_dd_insert" : "ep_glorantha_runes/hooks"
      },
      "client_hooks": {
        "postAceInit": "ep_glorantha_runes/static/js/index",
        "aceInitialized": "ep_glorantha_runes/static/js/index",
        "aceCreateDomLine": "ep_glorantha_runes/static/js/index",
        "aceAttribsToClasses": "ep_glorantha_runes/static/js/index",
        "aceInitInnerdocbodyHead": "ep_glorantha_runes/static/js/index"
      }
    }
  ]
}
